<?xml version="1.0" encoding="utf-8"?>
<resources>
	<string name="app_name">Tasks</string>
	<string name="package_name">com.tasks.android</string>
	<string name="developer">© Pocket Brilliance Limited %s</string>
	<string name="prefs_app">pref_key_storage_app</string>
	<string name="prefs_notification">pref_key_storage_notification</string>
	<string name="prefs_backup_restore">pref_key_backup_restore</string>
	<string name="navigation_drawer_open">Otevřít</string>
	<string name="navigation_drawer_close">Zavřít</string>
	<string name="navigation_drawer_title">Seznamy</string>
	<string name="action_delete_task_list">Smazat podseznam</string>
	<string name="action_add_task_list">Nový seznam</string>
	<string name="action_task_list_order">Změnit pořadí seznamů</string>
	<string name="action_send_feedback">Poslat zpětnou vazbu</string>
	<string name="action_settings">Nastavení</string>
	<string name="action_refresh">Obnovit</string>
	<string name="action_developer">DEVELOPER</string>
	<string name="action_delete_task">Smazat úkol</string>
	<string name="action_share_task">Sdílet úkol</string>
	<string name="action_move_task">Přesunout úkol</string>
	<string name="action_share_task_list">Sdílet seznam</string>
	<string name="action_edit_task_list">Upravit seznam</string>
	<string name="action_edit_sub_list">Upravit podseznam</string>
	<string name="action_reorder_sub_task_lists">Změnit pořadí podseznamů</string>
	<string name="action_clear_completed">Smazat dokončené</string>
	<string name="action_sort_task_list">Seřadit</string>
	<string name="action_uncheck_completed">Zrušit zaškrtnutí dokončených</string>
	<string name="action_search">Hledat</string>
	<string name="action_duplicate_list">Kopírovat podseznam</string>
	<string name="action_donate">Darovat</string>
	<string name="action_hide_completed">Skrýt dokončené</string>
	<string name="action_duplicate_task">Kopírovat úkol</string>
	<string name="action_add_filtered_list">Nový filtrovaný seznam</string>
	<string name="action_help">Nápověda</string>
	<string name="action_completed_all">Dokončit vše</string>
	<string name="action_default_list">Výchozí seznam při otevření aplikace</string>
	<string name="action_default_list_option">Naposledy zobrazený seznam</string>
	<string name="action_deleted_items">Smazané položky</string>
	<string name="action_delete_all">Smazat vše</string>
	<string name="action_add_to_calendar">Přidat do kalendáře</string>
	<string name="action_move_sub_task_list">Přesunout podseznam</string>
	<string name="action_move_task_to_top">Přejděte na začátek</string>
	<string name="action_move_task_to_bottom">Přejděte na konec</string>
	<string name="title_notes">Poznámky</string>
	<string name="title_task_name">Název úkolu</string>
	<string name="title_snooze">Odložit upozornění pro:</string>
	<string name="title_task_list">Seznam</string>
	<string name="title_reminder">Upozornění</string>
	<string name="title_complete">Dokončeno</string>
	<string name="title_created">Vytvořeno</string>
	<string name="title_task_list_name">Název seznamu</string>
	<string name="title_sub_task_list_name">Název podseznamu</string>
	<string name="title_filtered_list_name">Název filtrovaného seznamu</string>
	<string name="title_reminder_at">\@</string>
	<string name="title_repeat">Opakovat</string>
	<string name="title_share_task">Sdílet úkol s&#8230;</string>
	<string name="title_share_task_list">Sdílet seznam úkolů s&#8230;</string>
	<string name="title_about_settings">O aplikaci</string>
	<string name="title_build_version">Verze</string>
	<string name="title_app_settings">Nastavení aplikace</string>
	<string name="title_list_settings">Nastavení seznamu úkolů</string>
	<string name="title_settings_quick_add">Zobrazit rychlé vytvoření úkolu</string>
	<string name="title_settings_auto_link">Automaticky vytvářet odkazy v textu</string>
	<string name="title_highlight">Zvýraznění</string>
	<string name="title_settings_sort_completed">Přesunout dokončené úkoly</string>
	<string name="title_setting_backup">Zálohování</string>
	<string name="title_setting_restore">Obnovení</string>
	<string name="title_send_backup">Odeslat soubor se zálohou?</string>
	<string name="title_priority">Priorita</string>
	<string name="title_backup_restore_settings">Záloha/obnovení dat</string>
	<string name="title_settings_compact_mode">Způsob zobrazení</string>
	<string name="title_settings_delete_confirmation">Potvrdit smazání seznamu</string>
	<string name="title_settings_sub_task_list">Informace v záhlaví podseznamů</string>
	<string name="title_settings_menu_list">Informace v menu seznamů</string>
	<string name="title_settings_insert_new_tasks">Kam vkládat nové úkoly?</string>
	<string name="title_settings_swipe_to_delete_enabled">Povolit mazání gestem</string>
	<string name="title_settings_keep_screen_on">Nevypínat displej</string>
	<string name="title_settings_note_view">Zobrazení poznámek k úkolu</string>
	<string name="title_share_tasks_app">Sdílet aplikaci Tasks s přáteli</string>
	<string name="title_nominated_list">Kde se mají zobrazovat dokončené úkoly?</string>
	<string name="title_notification_settings">Nastavení oznámení/budíku</string>
	<string name="title_notification_led">LED</string>
	<string name="title_notification_vibrate">Vibrace</string>
	<string name="title_notification_sound">Zvuk oznámení</string>
	<string name="title_notification_alarm_sound">Zvuk budíku</string>
	<string name="title_due_date">Termín</string>
	<string name="title_reminder_type">Typ upozornění</string>
	<string name="title_repeat_until">Opakovat dokud</string>
	<string name="title_task_settings">Nastavení úkolů</string>
	<string name="title_settings_show_completed_date">Zobrazit celé datum dokončení</string>
	<string name="title_privacy_policy">Zásady ochrany osobních údajů</string>
	<string name="title_list_color">Barva</string>
	<string name="title_filter_lists">Podseznam</string>
	<string name="title_date">Datum</string>
	<string name="title_include_overdue">Zahrnout promeškané úkoly</string>
	<string name="title_notification_persistent">Trvalé oznámení</string>
	<string name="title_settings_show_calendar">Zobrazit kalendář</string>
	<string name="title_calendar_list">Kalendář</string>
	<string name="title_settings_enable_reminder">Zapnout upozornění</string>
	<string name="title_settings_alarm_duration">Délka budíku</string>
	<string name="title_settings_show_list_color">Zobrazit barvu seznamu</string>
	<string name="title_complete_clears_notification">Dokončení úkolu smaže oznámení</string>
	<string name="title_settings_custom_snooze_duration">Vlastní délka odložení</string>
	<string name="title_sub_tasks">Podúkoly</string>
	<string name="title_theme">Motiv</string>
	<string name="title_sub_task_name">Název podúkolu</string>
	<string name="title_settings_vibrate_ui">Vibrace</string>
	<string name="title_settings_verbose_date_time">Zobrazit datum a čas</string>
	<string name="title_settings_auto_link_text_color">Barva automatického odkazu</string>
	<string name="title_settings_default_reminder_type">Výchozí typ upozornění</string>
	<string name="title_widget_settings_show_fab">Zobrazit tlačítko Přidat</string>
	<string name="title_widget_settings_background_alpha">Průhlednost pozadí</string>
	<string name="title_widget_settings_list_item_alpha">Seznam průhlednosti položek</string>
	<string name="title_widget_settings_font_size">Velikost písma</string>
	<string name="title_settings_remove_deleted_items_days">Odstranit smazané položky starší než</string>
	<string name="hint_new_task_list">Pojmenovat&#8230;</string>
	<string name="hint_quick_add">Rychle přidat úkol&#8230;</string>
	<string name="hint_search">Prohledat úkoly</string>
	<string name="hint_notes">Klepnutím přidat poznámku</string>
	<string name="alert_ok">OK</string>
	<string name="alert_save">ULOŽIT</string>
	<string name="alert_cancel">ZRUŠIT</string>
	<string name="alert_send">ODESLAT</string>
	<string name="alert_undo">ZPĚT</string>
	<string name="alert_delete">SMAZAT</string>
	<string name="alert_about_title">O aplikaci</string>
	<string name="alert_about_message">Tasks (Úkoly) je jednoduchá aplikace na správu úkolů, která upřednostňuje praktičnost a použitelnost. Organizujte svůj zaneprázdněný život pomocí Tasks.</string>
	<string name="alert_rate_main_title">⭐ Podpořte nás</string>
	<string name="alert_rate_main_message">Je naše aplikace užitečná? Pomáháme vám s organizací času?</string>
	<string name="alert_rate_main_ok">ANO</string>
	<string name="alert_rate_main_cancel">NE</string>
	<string name="alert_rate_positive_title">Skvělé!</string>
	<string name="alert_rate_positive_message">Aplikace Tasks (Úkoly) se stále vyvíjí. Pokud ji milujete, ohodnoťte nás (opravdu nám to pomůže)!</string>
	<string name="alert_rate_positive_ok">ANO, MILUJU JI</string>
	<string name="alert_rate_positive_cancel">NE, DÍKY</string>
	<string name="alert_rate_negative_title">Můžete nám prosím říci proč?</string>
	<string name="alert_rate_negative_message">Něco jsme přehlédli? Máte nějaký nápad? Dejte nám prosím vědět, protože na aplikaci Tasks neustále pracujeme.</string>
	<string name="alert_rate_negative_ok">POSLAT ZPĚTNOU VAZBU</string>
	<string name="alert_rate_negative_cancel">NE, DÍKY</string>
	<string name="alert_help_ok">OK, ROZUMÍM</string>
	<string name="alert_chooser_title">Přesunout do</string>
	<string name="alert_widget_chooser_title">Změnit</string>
	<string name="alert_repeat_chooser_title">Frekvence opakování</string>
	<string name="alert_repeat_warning_title">Nastavení upozornění</string>
	<string name="alert_task_list_reorder_title">Seřadit seznamy úkolů</string>
	<string name="alert_sub_task_list_reorder_title">Změnit pořadí podseznamů</string>
	<string name="alert_repeat_warning_message">Nastavení data po 28. dni v měsíci může způsobit, že každý měsíc nemusí být k tomuto datu zobrazena upozornění.</string>
	<string name="alert_task_deleted">Úkol odstraněn!</string>
	<string name="alert_tasks_deleted">Úkoly odstraněny!</string>
	<string name="alert_sort_chooser_title">Seřadit seznam podle:</string>
	<string name="alert_uncheck_completed">Zrušit zaškrtnutí dokončených</string>
	<string name="alert_task_list_deleted">Seznam úkolů odstraněn!</string>
	<string name="alert_send_backup">Chcete nyní soubor zálohy odeslat? Pošlete si ho e-mailem, pokud ho potřebujete přenést do jiného telefonu.</string>
	<string name="alert_priority_title">Priorita úkolu</string>
	<string name="alert_backup_no_storage">Externí úložiště není dostupné!</string>
	<string name="alert_backup_cant_write_file">Není možné vytvořit soubor zálohy!</string>
	<string name="alert_backup_error_writing_data">Chyba při zápisu dat zálohy!</string>
	<string name="alert_restore_no_storage">Externí úložiště není dostupné</string>
	<string name="alert_restore_error_reading_file">Chyba: soubor nelze načíst!</string>
	<string name="alert_restore_error_file_not_found">Chyba: soubor nebyl nalezen!</string>
	<string name="alert_restore_success">Data byla úspěšně obnovena z</string>
	<string name="alert_restore_version_mismatch">Nelze obnovit. Neshoda verzí aplikace</string>
	<string name="alert_no_email_client">Nenalezen žádný e-mailový klient</string>
	<string name="alert_task_name_required">Vyžadován název úkolu</string>
	<string name="alert_thank_you">Děkuji Vám za Vaši štědrost :)</string>
	<string name="alert_delete_ok">ANO, SMAZAT</string>
	<string name="alert_delete_title">Smazat seznam</string>
	<string name="alert_delete_message">Tímto se odstraní také všechny úkoly v tomto seznamu. Jste si jistí?</string>
	<string name="alert_send_feedback_title">Jak Vám můžeme pomoci?</string>
	<string name="alert_whats_new_title">Co je nového</string>
	<string name="alert_restore_error_number_format">Neshoda formátů čísel</string>
	<string name="alert_restore_error_date_format_title">Chyba formátu data</string>
	<string name="alert_restore_error_date_format_message">Zobrazit on-line nápovědu?</string>
	<string name="alert_days_of_week_title">Dny v týdnu</string>
	<string name="alert_advanced_repeat_title">Pokročilé opakování</string>
	<string name="alert_split_quick_add_title">Rozdělit na více úkolů?</string>
	<string name="alert_split_quick_add_message">Byla nalezena zalomení řádků, přejete si text rozdělit na více úkolů?</string>
	<string name="alert_split_ok">ANO, ROZDĚLIT</string>
	<string name="alert_split_no">NE</string>
	<string name="alert_reminder_warning_title">Nastavení upozornění</string>
	<string name="alert_reminder_warning_message">Nastavení data v minulosti nezobrazí upozornění</string>
	<string name="alert_reminder_added">Upozornění v:</string>
	<string name="alert_task_modified_title">Úkol upraven</string>
	<string name="alert_task_modified">Udělali jste změny. Chcete je uložit?</string>
	<string name="alert_list_name_required">Vyžadován název seznamu</string>
	<string name="alert_due_days_message">Kolik dní dopředu si přejete zobrazit?</string>
	<string name="alert_include_overdue_message">Promeškané úkoly dnešního dne jsou vždy zahrnuty</string>
	<string name="alert_reminder_advance_title">Upozornění před termínem</string>
	<string name="alert_missing_due_date">Určete kdy, takže nejdříve nastavte termín.</string>
	<string name="alert_complete_all">Dokončit vše</string>
	<string name="alert_restore_permission_disabled">Přístup do externího úložiště není povolen!</string>
	<string name="alert_task_list_chooser_title">Seznam úkolů</string>
	<string name="alert_import_success">Data úspěšně importovány z</string>
	<string name="alert_import">Importuji data. Prosím čekejte&#8230;</string>
	<string name="alert_move_sub_task_list_warning_title">Pozor, přesouvám!</string>
	<string name="alert_move_sub_task_list_warning_message">Není možné přesunout poslední podseznam. Seznam úkolů musí mít alespoň jeden podseznam.</string>
	<string name="alert_syncing">Úkoly se synchronizují&#8230;</string>
	<string name="alert_sync">Synchronizace</string>
	<string name="alert_donate">Miluje Tasks (Úkoly)? Urychlete vývoj, kupte vývojáři kávu :)</string>
	<string name="help_no_task_lists_title">Začněte organizovat svůj život</string>
	<string name="help_no_task_lists_message">Klepněte na tlačítko menu a přidejte svůj první seznam úkolů</string>
	<string name="help_no_tasks_title">Ještě nemáte žádné úkoly</string>
	<string name="help_no_tasks_message">Klepnutím na tlačítko vytvořte nový úkol nebo použijte rychlé přidání pro jednoduché úkoly</string>
	<string name="help_swipe_delete_title">Jak úkol smazat?</string>
	<string name="help_swipe_delete_message">Posuňte úkol vlevo nebo vpravo</string>
	<string name="help_reorder_title">Chcete seznamy seřadit podle priority?</string>
	<string name="help_reorder_message">Úkoly můžete seřadit pomocí úchytek napravo a svislým přetažením</string>
	<string name="help_no_task_list">Před přidáním úkolu vytvořte prosím nejdříve seznam úkolů</string>
	<string name="help_reminder_not_set">Žádné upozornění nenastaveno</string>
	<string name="help_unknown">Neznámé</string>
	<string name="help_settings_quick_add">Zobrazit rychlé přidání na konci seznamu úkolů. Nebude však zobrazeno u filtrovaných seznamů</string>
	<string name="help_settings_auto_link">URL, e-mailové adresy a telefonní čísla budou zobrazená jako odkaz</string>
	<string name="help_highlight">Úkol bude v seznamu zvýrazněný</string>
	<string name="help_settings_sort_completed">Přesunout dokončené úkoly na konec seznamu</string>
	<string name="help_settings_backup">Zálohovat data do místního souboru: /Download/tasks_backup.json pro přeposlání e-mailem na jiný telefon</string>
	<string name="help_settings_restore">Obnovit data ze souboru zálohy: /Download/tasks_backup.json což funguje pouze se zálohou vytvořenou stejnou verzí aplikace. Pokud potřebujete pomoc, napište nám e-mail na tasks.list.app@gmail.com. Obnovení vyžaduje, abyste podpořili vývoj úkolů s jednorázovým darem nebo premium předplatným.</string>
	<string name="help_settings_delete_confirmation">Požadovat potvrzení při odstraňování seznamu úkolů</string>
	<string name="help_settings_swipe_to_delete">Úkoly lze smazat vodorovným přetažením.</string>
	<string name="help_settings_keep_screen_on">Displej se nevypne, pokud jste v seznamu úkolů.</string>
	<string name="help_advanced_repeat">Každých</string>
	<string name="help_settings_show_completed_date">Zobrazit datum a čas dokončení úkolu</string>
	<string name="help_notification_persistent">Oznámení bude těžší odstranit</string>
	<string name="help_settings_show_calendar">Zobrazit úkoly v kalendáři. Poznámka: V tomto zobrazení jsou funkce omezeny</string>
	<string name="help_minutes">minut</string>
	<string name="help_settings_enable_reminder">Při vytváření úkolu vždy povolit upozornění.</string>
	<string name="help_settings_show_list_color">Zobrazit barvu seznamu u každého úkolu (neplatí pro filtrované seznamy)</string>
	<string name="help_complete_clears_notification">Dokončení úkolu smaže související oznámení (pokud je zobrazeno)</string>
	<string name="help_settings_vibrate_ui">Hmatová zpětná vazba.</string>
	<string name="help_settings_verbose_date_time">Vždy zobrazit datum a čas úkolu</string>
	<string name="help_fetching_price">Načítání ceny</string>
	<string name="notification_done_action_help">OZNAČIT JAKO DOKONČENÉ</string>
	<string name="notification_snooze_action_help">ODLOŽIT</string>
	<string name="shortcut_new_task_short_label">Nový úkol</string>
	<string name="shortcut_new_task_long_label">Nový úkol</string>
	<string name="shortcut_new_task_disabled_label">Nové úkoly nejsou povoleny</string>
	<string name="misc_today_lower">dnes</string>
	<string name="misc_today_camel">Dnes</string>
	<string name="misc_completed">Dokončeno</string>
	<string name="misc_copy_prefix">Kopírovat</string>
	<string name="misc_share_tasks_app_subject">Zde je odkaz na skvělou aplikaci, kterou používám.</string>
	<string name="misc_this_list">Tento seznam</string>
	<string name="misc_all">Vše</string>
	<string name="misc_share_uncompleted">\u25FB</string>
	<string name="misc_share_completed">\u2714</string>
	<string name="title_settings_auto_increment_reminder">Automatické připomenutí přírůstku</string>
	<string name="help_settings_auto_increment_reminder">Povoleno: připomenutí se zvyšuje automaticky, když je oznámení přijato Vypnuto: připomenutí se zvyšuje, když je úkol označen jako dokončený</string>
	<string name="alert_write_success">Data byla úspěšně zapsána do</string>
	<string name="title_export_csv">Export do souboru CSV</string>
	<string name="help_export_csv">Uložte data ve formátu hodnot oddělených čárkami (CSV). Bude uložen do adresáře / Stáhnout</string>
	<string name="notification_dismiss_action_help">PROPUSTIT</string>
	<string name="alert_days_of_week_warning_title">Volba chyby</string>
	<string name="title_settings_show_menu_on_back">Zobrazovat hlavní menu, když zpět stisknutí</string>
	<string name="help_settings_show_menu_on_back">Po stisknutí tlačítka zpět zobrazení menu místo ukončení aplikace.</string>
	<string name="title_summary_notification">oznámení Shrnutí</string>
	<string name="alert_days_of_week_warning_message">Je nutné vybrat alespoň jeden den.</string>
	<string name="alert_debug_info">Debug Info</string>
	<string name="help_settings_show_menu_on_open">Při otevření aplikace zobrazí hlavní menu.</string>
	<string name="title_settings_show_menu_on_open">Zobrazovat hlavní menu při otevírání aplikace</string>
	<string name="help_settings_sub_tasks_complete_task">Když jsou všechny dílčí úkoly kompletní nadřazená úloha bude rovněž označen jako vyřízená</string>
	<string name="title_settings_sub_tasks_complete_task">Dokončení všech dílčích úkolů dokončí úkol</string>
	<string name="plural_minute">minuta</string>
	<string name="plural_minutes">minut</string>
	<string name="plural_hour">hodina</string>
	<string name="plural_two_hours">hodiny</string>
	<string name="plural_hours">hodin</string>
	<string name="plural_day">den</string>
	<string name="plural_days">dnů</string>
	<string name="premium_one_backup_title">Automatické zálohování do cloud</string>
	<string name="title_settings_sync_on_open">Synchronizace při otevírání Úkoly</string>
	<string name="premium_one_device_to_device_sync_title">Zařízení k synchronizaci zařízení</string>
	<string name="alert_sync_complete">Vaše první synchronizace byla dokončena, budou data automaticky synchronizovány na pozadí při každém zavření aplikace</string>
	<string name="alert_delete_user_title">Smazat účet a všechna data?</string>
	<string name="premium_three_sync_data_information">Stačí kliknout na tlačítko synchronizovat a počkat na dokončení. V závislosti na rychlosti vašeho datového připojení a množství dat, to může trvat až jednu minutu, takže buďte trpěliví. Všechny následné synchronizace jsou inkrementální a budou tak rychlejší.</string>
	<string name="alert_retry_title">Opakovat?</string>
	<string name="premium_three_information">Pojďme zálohovat všechna data do cloudu. Je to šifrováné a bezpečné</string>
	<string name="premium_one_web_app_title">Web App</string>
	<string name="premium_three_sub_title">Děkujeme, že jste si vybrali Tasks(Úkoly) Premium</string>
	<string name="prefs_premium">pref_key_premium</string>
	<string name="premium_two_sub_title_two">2. Vyberte si předplatné</string>
	<string name="premium_one_backup_message">Nebojte se o svá data, je to šifrované, to je zálohována a je to bezpečné a zdravé</string>
	<string name="premium_continue">Pokračovat</string>
	<string name="title_settings_logout">smazat účet</string>
	<string name="premium_two_information">Pro vaši bezpečnost a pohodlí, Úkoly používá ověřování Google. Kliknutím na tlačítko pro přihlášení.</string>
	<string name="help_settings_sync_wifi_only">Synchronizace dat na pozadí, když jen na Wi-Fi. To se netýká strhnout k osvěžení</string>
	<string name="help_settings_sync_on_close">synchronizace dat z cloudu při zavření Úkoly</string>
	<string name="title_settings_sync_wifi_only">Sync na Wi-Fi pouze</string>
	<string name="help_settings_logout">Smazání účtu je trvalé. Všechny vaše data budou odstraněny z oblaku a nebudete moci získat zpět. Poznámka: to nebude zrušit předplatné musí být provedeno přes Obchodě Play.</string>
	<string name="premium_three_sync_now">nyní Sync</string>
	<string name="premium_two_sub_title">1. Přihlaste se k účtu Google</string>
	<string name="premium_title">úkoly Premium</string>
	<string name="premium_two_information_two">Vyberte požadovanou možnost předplatného:</string>
	<string name="title_premium_settings">Nastavení Premium</string>
	<string name="premium_one_device_to_device_sync_message">Mají tablet a telefon? Upravovat své úkoly na obou</string>
	<string name="title_premium_help">Premium help</string>
	<string name="title_settings_sync_on_close">Sync při zavírání Úkoly</string>
	<string name="alert_retry_message">Vypadá to, že máte neúplné nákupu. Nebudete muset platit znovu. Chtěli byste se opakovat?</string>
	<string name="alert_retry_ok">YES, RETRY</string>
	<string name="premium_one_sharing_title">sdílení seznamu</string>
	<string name="premium_one_sharing_message">Chcete se podělit o nákupní seznam s partnerem? Sdílení seznam je pro vás</string>
	<string name="premium_one_sub_title">Organizovat jako profík s</string>
	<string name="help_settings_sync_on_open">synchronizace dat z cloudu při otevření Úkoly</string>
	<string name="premium_one_information">Úkoly vždy uvedeny všechny funkce zdarma bez reklamy. Že se nemění, ale bohužel servery stojí peníze, takže potřebujeme nějakou pomoc, pokud byste chtěli použít následující:</string>
	<string name="help_settings_user_deleted">Účet a data smazána</string>
	<string name="help_settings_user_deleted_error">Chyba při pokusu o smazání účtu</string>
	<string name="action_upgrade_to_premium">Upgrade na Premium</string>
	<string name="alert_premium_expired">Premium vypršela</string>
	<string name="alert_error_updating_subscription">Došlo k chybě při přidávání předplatné. Prosím, napište mi na pomoc.</string>
	<string name="alert_error_creating_user">Došlo k chybě při pokusu o vytvoření účtu. Zkontrolujte sítě připojení a zkuste to znovu.</string>
	<string name="alert_error_title">Chyba</string>
	<string name="premium_one_support_development_title">Rozvoj podpůrné úlohy</string>
	<string name="premium_one_support_development_message">Úkoly je nezávisle vyvinuté aplikace, a to se spoléhá na podporu úžasných uživatelů je to.</string>
	<string name="alert_premium_expired_warning">Váš Úkoly Premium předplatné vypršelo. Můžete se zaregistrovat kdykoliv znovu.</string>
	<string name="alert_delete_message_filtered">Tím se odstraní filtrovaný seznam, ale vaše data zůstanou v původních seznamech. Jsi si jistá?</string>
	<string name="alert_delete_title_filtered">Delete filtrován seznam</string>
	<string name="title_widget_settings_move_add">Stisknutým tlačítkem přidat do nadpisu</string>
	<string name="title_settings_sub_tasks_expand_default">Dílčí úkoly byly rozšířeny</string>
	<string name="help_settings_sub_tasks_expand_default">Rozbalte dílčí úkoly v hlavním zobrazení seznamu. nové úkoly bude používat pouze toto nastavení</string>
	<string name="alert_notification_warning">Povolte spouštění úkolů na pozadí, abyste mohli přijímat oznámení / alarmy. Máte-li problémy s přijímáním oznámení / alarmy prosím pokladny často kladené otázky v on-line nápovědě k dispozici z hlavního menu nebo na adrese: <a href="https://mytasksapp.com/help/faqs#notifications">https://mytasksapp.com/help/faqs</a></string>
	<string name="premium_two_agreement">Výběrem předplatného budete požádáni o platbu prostřednictvím svého účtu Google PlayStore. Vaše předplatné se automaticky obnoví na stejnou dobu trvání a cenu, dokud jej nezrušíte. Chcete-li zrušit, viz Předplatné v Google PlayStore. Musíte zrušit alespoň 24 hodin před koncem aktuálního období. Přihlášením souhlasíte s našimi <a href="https://mytasksapp.com/legal/privacy-policy"> zásadami ochrany soukromí </a> a <a href="https://mytasksapp.com/legal/terms-of-service"> </a>. Pomoc s prémiovými funkcemi naleznete na <a href="https://mytasksapp.com/help/premium"> stránce nápovědy </a>.</string>
	<string name="premium_three_help">Pomoc s prémiovými funkcemi naleznete na <a href="https://mytasksapp.com/help/premium"> stránce nápovědy </a>.</string>
	<string name="title_settings_insert_new_sub_tasks">Tam, kde by se nové dílčí úkoly byly vloženy?</string>
	<string name="help_settings_strikethrough_completed">Přeškrtnutí název úkol a poznámky při dokončení úkolu</string>
	<string name="title_settings_strikethrough_completed">Přeškrtnutí dokončené úkoly</string>
	<string name="title_settings_account">Účet</string>
	<string name="premium_one_web_app_message">Kéž bys mohl upravit své úkoly na počítači? Teď můžeš :)</string>
	<string name="premium_upgrade">K dispozici pro uživatele Premium. Stačí přejít z hlavního menu.</string>
	<string name="title_settings_default_priority">výchozí priorita</string>
	<string name="plural_pixels">pixely</string>
	<string name="title_settings_task_padding">položka seznamu padding</string>
	<string name="alert_contact_support">Kontaktování podpory pro pomoc.</string>
	<string name="alert_premium_support_feature">Tato funkce je k dispozici pro ty, kteří s aktivním předplatným prémie, nebo kteří přispěli podpůrné úkoly tím, že dary. Chcete-li objednat nebo darovat jít do hlavního menu. Děkuji za vaši podporu.</string>
	<string name="help_duplicate_on_reset">Vést záznamy o svých dokončených opakujících se úkolů. Duplicitní opakující se úkony při označené jako dokončené.</string>
	<string name="title_recurring_task_reset">Kdy by se opakující úkoly resetovat?</string>
	<string name="title_save_recurring_task_history">Save opakující se historii úkol?</string>
	<string name="alert_upgrade_to_premium_message_three">⭐ synchronizovat mezi zařízeními?</string>
	<string name="alert_upgrade_to_premium_message_two">⭐ Chraňte svá data pomocí automatického zálohování cloud?</string>
	<string name="alert_upgrade_to_premium_message_one">⭐ byste chtěli upravit své úkoly z vašeho počítače?</string>
	<string name="alert_upgrade_to_premium_message_five">Chtěli byste se dozvědět více?</string>
	<string name="alert_upgrade_to_premium_message_four">⭐ Help rozvoj podpůrné úkoly?</string>
	<string name="help_relax_text">Čerstvý seznam, pojďme začít.</string>
	<string name="title_all_day">Celý den</string>
	<string name="title_tags">Tagy</string>
	<string name="premium_one_tags_title">Neomezené tagy</string>
	<string name="title_solid_switch">Pevný</string>
	<string name="hint_tags">Úkoly zdarma umožňuje 3 značky. Chcete více? Neomezené tagy dostupné pro uživatele Premium! Upgrade na úkoly Premium z hlavního menu.</string>
	<string name="alert_upgrade_to_premium_message_four_b">⭐ Neomezené značky?</string>
	<string name="help_tag_not_set">Vybrané žádné značky</string>
	<string name="title_tag_name">Název štítku</string>
	<string name="help_no_tags">Žádné značky. Přidejte nové značky z hlavní nabídky.</string>
	<string name="title_settings_tag_size">Velikost značky</string>
	<string name="help_settings_battery_optimisation">Povolte spouštění úkolů na pozadí, aby se zobrazovala oznámení a alarmy.</string>
	<string name="title_battery_optimisation">Mám potíže s připomenutím?</string>
	<string name="premium_two_yearly_billed">Ročně</string>
	<string name="premium_two_monthly_billed">Účtován měsíčně</string>
	<string name="premium_two_lifetime_billed">Účtován jednou</string>
	<string name="premium_two_yearly_title">Roční</string>
	<string name="premium_two_lifetime_title">Život</string>
	<string name="premium_two_monthly_title">Měsíční</string>
	<string name="premium_two_most_popular">Nejpopulárnější</string>
	<string name="help_list_not_found">Klepnutím vyberte seznam.</string>
	<string name="help_settings_sync">Synchronizační data s cloudem.</string>
	<string name="help_settings_add_from_notification">Vytvořte úkoly přímo z trvalého oznámení. Snadnější a rychlejší.</string>
	<string name="hint_add_task">Přidat úkol</string>
	<string name="title_settings_add_from_notification">Přidejte úkoly z oznamovacího panelu</string>
	<string name="title_settings_last_sync">Poslední synchronizace</string>
	<string name="alert_backup_nudge">Vypadá to, že jste na chvíli neučinili data. Proveďte zálohu z nastavení úkolů. Automatické zálohování Cloud je k dispozici pro uživatele Premium.</string>
	<string name="hint_add_task_info">Klepnutím přidáte úkol. Zakázat nastavení aplikace.</string>
	<string name="premium_two_promo">30% sleva</string>
	<string name="alert_black_friday_message">⭐ Zvláštní poděkování dostanete 30% slevu na předplatné úkoly. Nabídka končí pondělí. Upgrade na Premium z hlavního menu.</string>
	<string name="alert_black_friday_title">Černý pátek sleva</string>
	<string name="title_mute_alarm_on_call">Ztlumit alarm při telefonování</string>
	<string name="help_settings_mute_alarm_on_call">Zobrazit oznámení namísto alarmu.</string>
	<string name="help_settings_multi_line_quick_add">Je-li povoleno povolit vstup multifunkčního textu. Po zakázání Použijte klávesu Enter pro ještě rychlejší vstup.</string>
	<string name="title_settings_multi_line_quick_add">Multi line rychlé přidání</string>
	<string name="alert_new">NOVÝ</string>
	<string name="alert_save_and_add">ULOŽIT A PŘIDAT</string>
	<string name="help_create_share_link">Klepnutím vygenerujete odkaz na sdílení</string>
	<string name="title_members">Členové</string>
	<string name="title_admin">Admin</string>
	<string name="title_copy_link">Odkaz na sdílení kopírování</string>
	<string name="action_manage_shared_list">Správa seznamu</string>
	<string name="title_shared_list_name">Název sdíleného seznamu</string>
	<string name="alert_sync_already_in_progress">Synchronizace již probíhá</string>
	<string name="help_cannot_create_share_link">Nelze generovat pozvání</string>
	<string name="title_list_unlocked">Seznam odemčený</string>
	<string name="help_list_locked">Tento seznam se nemohou připojit k žádným novým členům.</string>
	<string name="title_create_link">Vytvořte odkaz na sdílení</string>
	<string name="title_list_locked">Seznam zamčený</string>
	<string name="help_link_copied">Odkaz zkopírovaný do schránky</string>
	<string name="action_add_shared_list">Nový sdílený seznam</string>
	<string name="help_list_unlocked">Nový člen se může připojit pomocí odkazu na pozvání.</string>
	<string name="action_default_add_from_list">Výchozí podsestav</string>
	<string name="title_settings_auto_number_tasks">Úkoly automatického čísla</string>
	<string name="help_settings_auto_number_sub_tasks">Automaticky očísejte každou dílčí úlohu v seznamu.</string>
	<string name="title_settings_auto_number_sub_tasks">Sub úkoly automatického čísla</string>
	<string name="help_settings_auto_number_tasks">Automaticky očísejte každý úlohu v seznamu.</string>
	<string name="misc_tomorrow">Zítra</string>
	<string name="alert_set">Soubor</string>
	<string name="action_instagram">Instagram</string>
	<string name="alert_whats_new_instagram">⭐ Nyní jsem na Instagramu. Chtěli byste vidět, na čem pracuji? Vidět v zákulisí? Podívejte se, jak jsou aplikace vytvořeny nebo jen pomáhají podporovat mou aplikaci. Sledujte mě na Instagramu. Na zdraví, Steve</string>
	<string name="action_youtube">YouTube</string>
	<string name="help_out_of_memory">Mimo paměť - soubor příliš velký</string>
	<string name="alert_whats_new_image_attachments">⭐ Přílohy obrázků pro úkoly, k dispozici zdarma, všem. Pokud se vám to líbí, zvažte prosím ukázat své uznání 5hvězdičkovým recenzí na Google Playstore. Na zdraví, Steve</string>
	<string name="title_attachment">Příloha</string>
	<string name="mics_steps_to_reproduce">Kroky k reprodukci problému:</string>
	<plurals name="misc_minute">
		<item quantity="one">%d minuta</item>
		<item quantity="few">%d minut</item>
		<item quantity="other">%d minut</item>
		<item quantity="many">%d minut</item>
	</plurals>
	<plurals name="misc_hour">
		<item quantity="one">%d hodina</item>
		<item quantity="few">%d hodin</item>
		<item quantity="other">%d hodin</item>
		<item quantity="many">%d hodin</item>
	</plurals>
	<plurals name="misc_day">
		<item quantity="one">%d den</item>
		<item quantity="few">%d dnů</item>
		<item quantity="other">%d dnů</item>
		<item quantity="many">%d dnů</item>
	</plurals>
</resources>
